{
  "data": [
    {
      "id": "1601929527730778112",
      "text": "test #test",
      "edit_history_tweet_ids": [
        "1601929527730778112"
      ],
      "author_id": "194534641"
    },
    {
      "id": "1601995732554117120",
      "text": "テスト #test",
      "edit_history_tweet_ids": [
        "1601995732554117120"
      ],
      "author_id": "194534641"
    },
    {
      "id": "1609529692079673344",
      "text": "#test",
      "edit_history_tweet_ids": [
        "1609529692079673344"
      ],
      "author_id": "194534641"
    },
    {
      "id": "1609806518177927175",
      "text": "#test",
      "edit_history_tweet_ids": [
        "1609806518177927175"
      ],
      "author_id": "194534641"
    },
    {
      "id": "1609856686063489026",
      "text": "てすと #test",
      "edit_history_tweet_ids": [
        "1609856686063489026"
      ],
      "author_id": "194534641"
    }
  ],
  "includes": {
    "users": [
      {
        "protected": false,
        "name": "雪猫.yml",
        "profile_image_url": "https://pbs.twimg.com/profile_images/1596544054942371842/yYCwsXQD_normal.jpg",
        "url": "https://t.co/nB3cx3Lxps",
        "username": "snow_cait",
        "id": "194534641"
      }
    ]
  }
}